README.md
setup.py
py_slack_term/__init__.py
py_slack_term/main.py
py_slack_term/test_script.py
py_slack_term.egg-info/PKG-INFO
py_slack_term.egg-info/SOURCES.txt
py_slack_term.egg-info/dependency_links.txt
py_slack_term.egg-info/entry_points.txt
py_slack_term.egg-info/requires.txt
py_slack_term.egg-info/top_level.txt
py_slack_term/lib/__init__.py
py_slack_term/lib/config.py
py_slack_term/lib/logger.py
py_slack_term/lib/UI/__init__.py
py_slack_term/lib/UI/main.py
py_slack_term/lib/UI/themes.py
py_slack_term/lib/UI/forms/__init__.py
py_slack_term/lib/UI/forms/conversations_window.py
py_slack_term/lib/UI/widgets/__init__.py
py_slack_term/lib/UI/widgets/channel_messages.py
py_slack_term/lib/UI/widgets/channel_selector.py
py_slack_term/lib/UI/widgets/debug_widget.py
py_slack_term/lib/UI/widgets/message_composer.py
py_slack_term/lib/npyscreen_patch/__init__.py
py_slack_term/lib/npyscreen_patch/buffer_pager.py
py_slack_term/lib/slack_client/__init__.py
py_slack_term/lib/slack_client/API/__init__.py
py_slack_term/lib/slack_client/API/channel.py
py_slack_term/lib/slack_client/API/client.py
py_slack_term/lib/slack_client/API/message.py
py_slack_term/lib/slack_client/API/user.py
py_slack_term/lib/slack_client/RTM/__init__.py
py_slack_term/lib/slack_client/RTM/rtmclient.py