Metadata-Version: 1.0
Name: py-slack-term
Version: 0.1.11
Summary: Terminal based client for Slack
Home-page: https://github.com/chestm007/py_slack_terminal
Author: max
Author-email: chestm007@hotmail.com
License: GPL-2.0
Platform: UNKNOWN
